{
  "code": "E08000029",
  "name": "Solihull",
  "type": "lad",
  "area": 17828.78,
  "count": 331,
  "parents": [
    {
      "code": "E12000005",
      "name": "West Midlands",
      "type": "rgn"
    },
    {
      "code": "E92000001",
      "name": "England",
      "type": "ctry"
    },
    {
      "code": "K04000001",
      "name": "England and Wales",
      "type": "ew"
    }
  ],
  "children": [
    {
      "code": "E02002081",
      "name": "Solihull 001",
      "type": "msoa"
    },
    {
      "code": "E02002082",
      "name": "Solihull 002",
      "type": "msoa"
    },
    {
      "code": "E02002083",
      "name": "Solihull 003",
      "type": "msoa"
    },
    {
      "code": "E02002084",
      "name": "Solihull 004",
      "type": "msoa"
    },
    {
      "code": "E02002085",
      "name": "Solihull 005",
      "type": "msoa"
    },
    {
      "code": "E02002086",
      "name": "Solihull 006",
      "type": "msoa"
    },
    {
      "code": "E02002087",
      "name": "Solihull 007",
      "type": "msoa"
    },
    {
      "code": "E02002088",
      "name": "Solihull 008",
      "type": "msoa"
    },
    {
      "code": "E02002089",
      "name": "Solihull 009",
      "type": "msoa"
    },
    {
      "code": "E02002090",
      "name": "Solihull 010",
      "type": "msoa"
    },
    {
      "code": "E02002091",
      "name": "Solihull 011",
      "type": "msoa"
    },
    {
      "code": "E02002092",
      "name": "Solihull 012",
      "type": "msoa"
    },
    {
      "code": "E02002093",
      "name": "Solihull 013",
      "type": "msoa"
    },
    {
      "code": "E02002094",
      "name": "Solihull 014",
      "type": "msoa"
    },
    {
      "code": "E02002095",
      "name": "Solihull 015",
      "type": "msoa"
    },
    {
      "code": "E02002096",
      "name": "Solihull 016",
      "type": "msoa"
    },
    {
      "code": "E02002097",
      "name": "Solihull 017",
      "type": "msoa"
    },
    {
      "code": "E02002098",
      "name": "Solihull 018",
      "type": "msoa"
    },
    {
      "code": "E02002099",
      "name": "Solihull 019",
      "type": "msoa"
    },
    {
      "code": "E02002101",
      "name": "Solihull 021",
      "type": "msoa"
    },
    {
      "code": "E02002102",
      "name": "Solihull 022",
      "type": "msoa"
    },
    {
      "code": "E02002103",
      "name": "Solihull 023",
      "type": "msoa"
    },
    {
      "code": "E02002104",
      "name": "Solihull 024",
      "type": "msoa"
    },
    {
      "code": "E02002105",
      "name": "Solihull 025",
      "type": "msoa"
    },
    {
      "code": "E02002106",
      "name": "Solihull 026",
      "type": "msoa"
    },
    {
      "code": "E02002107",
      "name": "Solihull 027",
      "type": "msoa"
    },
    {
      "code": "E02002108",
      "name": "Solihull 028",
      "type": "msoa"
    },
    {
      "code": "E02002109",
      "name": "Solihull 029",
      "type": "msoa"
    },
    {
      "code": "E02006808",
      "name": "Solihull 030",
      "type": "msoa"
    }
  ],
  "bounds": [
    [
      -1.87204,
      52.34772
    ],
    [
      -1.59285,
      52.51448
    ]
  ],
  "data": {
    "population": {
      "perc": {
        "2001": {
          "female": 51.54,
          "male": 48.46
        },
        "2011": {
          "female": 51.44,
          "male": 48.56
        },
        "change": {
          "female": -0.1,
          "male": 0.1
        }
      },
      "perc_rank": {
        "2001": {
          "female": 105.0,
          "male": 226.0
        },
        "2011": {
          "female": 54.0,
          "male": 277.0
        },
        "change": {
          "female": 91.0,
          "male": 238.0
        }
      },
      "value": {
        "2001": {
          "all": 199517.0,
          "female": 102834.0,
          "male": 96683.0
        },
        "2011": {
          "all": 206674.0,
          "female": 106322.0,
          "male": 100352.0
        },
        "change": {
          "all": 3.59,
          "female": 3.39,
          "male": 3.79
        }
      },
      "value_rank": {
        "2001": {
          "all": 80.0,
          "female": 80.0,
          "male": 81.0
        },
        "2011": {
          "all": 84.0,
          "female": 83.0,
          "male": 87.0
        },
        "change": {
          "all": 256.0,
          "female": 251.0,
          "male": 270.0
        }
      }
    },
    "welsh": {
      "perc": {
        "2001": {
          "AllOver3": NaN,
          "SpeaksWelsh": NaN
        },
        "2011": {
          "AllOver3": NaN,
          "SpeaksWelsh": NaN
        },
        "change": {
          "AllOver3": NaN,
          "SpeaksWelsh": NaN
        }
      },
      "perc_rank": {
        "2001": {
          "AllOver3": NaN,
          "SpeaksWelsh": NaN
        },
        "2011": {
          "AllOver3": NaN,
          "SpeaksWelsh": NaN
        },
        "change": {
          "AllOver3": NaN,
          "SpeaksWelsh": NaN
        }
      },
      "value": {
        "2001": {
          "AllOver3": NaN,
          "SpeaksWelsh": NaN,
          "all": NaN
        },
        "2011": {
          "AllOver3": NaN,
          "SpeaksWelsh": NaN,
          "all": NaN
        },
        "change": {
          "AllOver3": NaN,
          "SpeaksWelsh": NaN,
          "all": NaN
        }
      },
      "value_rank": {
        "2001": {
          "AllOver3": NaN,
          "SpeaksWelsh": NaN,
          "all": NaN
        },
        "2011": {
          "AllOver3": NaN,
          "SpeaksWelsh": NaN,
          "all": NaN
        },
        "change": {
          "AllOver3": NaN,
          "SpeaksWelsh": NaN,
          "all": NaN
        }
      }
    },
    "care": {
      "perc": {
        "2001": {
          "1to19hoursWeek": 7.57,
          "20to49hoursWeek": 1.05,
          "40PlushoursWeek": 1.9,
          "noCare": 89.48
        },
        "2011": {
          "1to19hoursWeek": 7.78,
          "20to49hoursWeek": 1.4,
          "40PlushoursWeek": 2.48,
          "noCare": 88.33
        },
        "change": {
          "1to19hoursWeek": 0.21,
          "20to49hoursWeek": 0.35,
          "40PlushoursWeek": 0.58,
          "noCare": -1.15
        }
      },
      "perc_rank": {
        "2001": {
          "1to19hoursWeek": 69.0,
          "20to49hoursWeek": 146.0,
          "40PlushoursWeek": 180.0,
          "noCare": 211.0
        },
        "2011": {
          "1to19hoursWeek": 37.0,
          "20to49hoursWeek": 129.0,
          "40PlushoursWeek": 144.0,
          "noCare": 264.0
        },
        "change": {
          "1to19hoursWeek": 38.0,
          "20to49hoursWeek": 69.0,
          "40PlushoursWeek": 37.0,
          "noCare": 302.0
        }
      },
      "value": {
        "2001": {
          "1to19hoursWeek": 15095.0,
          "20to49hoursWeek": 2092.0,
          "40PlushoursWeek": 3800.0,
          "all": 199517.0,
          "noCare": 178530.0
        },
        "2011": {
          "1to19hoursWeek": 16084.0,
          "20to49hoursWeek": 2896.0,
          "40PlushoursWeek": 5133.0,
          "all": 206674.0,
          "noCare": 182561.0
        },
        "change": {
          "1to19hoursWeek": 6.55,
          "20to49hoursWeek": 38.43,
          "40PlushoursWeek": 35.08,
          "all": 3.59,
          "noCare": 2.26
        }
      },
      "value_rank": {
        "2001": {
          "1to19hoursWeek": 59.0,
          "20to49hoursWeek": 91.0,
          "40PlushoursWeek": 94.0,
          "all": 80.0,
          "noCare": 82.0
        },
        "2011": {
          "1to19hoursWeek": 50.0,
          "20to49hoursWeek": 86.0,
          "40PlushoursWeek": 77.0,
          "all": 84.0,
          "noCare": 88.0
        },
        "change": {
          "1to19hoursWeek": 112.0,
          "20to49hoursWeek": 152.0,
          "40PlushoursWeek": 85.0,
          "all": 256.0,
          "noCare": 274.0
        }
      }
    },
    "religion": {
      "perc": {
        "2001": {
          "Buddhist": 0.17,
          "Christian": 78.19,
          "Hindu": 0.93,
          "Jewish": 0.19,
          "Muslim": 0.82,
          "Noreligion": 12.05,
          "Otherreligion": 0.15,
          "Religionnotstated": 6.72,
          "Sikh": 0.78
        },
        "2011": {
          "Buddhist": 0.21,
          "Christian": 65.6,
          "Hindu": 1.78,
          "Jewish": 0.17,
          "Muslim": 2.54,
          "Noreligion": 21.38,
          "Otherreligion": 0.28,
          "Religionnotstated": 6.35,
          "Sikh": 1.7
        },
        "change": {
          "Buddhist": 0.04,
          "Christian": -12.59,
          "Hindu": 0.85,
          "Jewish": -0.02,
          "Muslim": 1.72,
          "Noreligion": 9.33,
          "Otherreligion": 0.13,
          "Religionnotstated": -0.37,
          "Sikh": 0.92
        }
      },
      "perc_rank": {
        "2001": {
          "Buddhist": 179.0,
          "Christian": 79.0,
          "Hindu": 62.0,
          "Jewish": 99.0,
          "Muslim": 127.0,
          "Noreligion": 252.0,
          "Otherreligion": 285.0,
          "Religionnotstated": 279.0,
          "Sikh": 38.0
        },
        "2011": {
          "Buddhist": 259.0,
          "Christian": 86.0,
          "Hindu": 47.0,
          "Jewish": 103.0,
          "Muslim": 92.0,
          "Noreligion": 269.0,
          "Otherreligion": 288.0,
          "Religionnotstated": 280.0,
          "Sikh": 23.0
        },
        "change": {
          "Buddhist": 314.0,
          "Christian": 184.0,
          "Hindu": 29.0,
          "Jewish": 202.0,
          "Muslim": 67.0,
          "Noreligion": 250.0,
          "Otherreligion": 151.0,
          "Religionnotstated": 167.0,
          "Sikh": 8.0
        }
      },
      "value": {
        "2001": {
          "Buddhist": 344.0,
          "Christian": 155993.0,
          "Hindu": 1850.0,
          "Jewish": 389.0,
          "Muslim": 1637.0,
          "Noreligion": 24033.0,
          "Otherreligion": 299.0,
          "Religionnotstated": 13406.0,
          "Sikh": 1566.0,
          "all": 199517.0
        },
        "2011": {
          "Buddhist": 430.0,
          "Christian": 135572.0,
          "Hindu": 3684.0,
          "Jewish": 353.0,
          "Muslim": 5247.0,
          "Noreligion": 44187.0,
          "Otherreligion": 569.0,
          "Religionnotstated": 13128.0,
          "Sikh": 3504.0,
          "all": 206674.0
        },
        "change": {
          "Buddhist": 25.0,
          "Christian": -13.09,
          "Hindu": 99.14,
          "Jewish": -9.25,
          "Muslim": 220.53,
          "Noreligion": 83.86,
          "Otherreligion": 90.3,
          "Religionnotstated": -2.07,
          "Sikh": 123.75,
          "all": 3.59
        }
      },
      "value_rank": {
        "2001": {
          "Buddhist": 106.0,
          "Christian": 59.0,
          "Hindu": 54.0,
          "Jewish": 75.0,
          "Muslim": 109.0,
          "Noreligion": 108.0,
          "Otherreligion": 186.0,
          "Religionnotstated": 100.0,
          "Sikh": 38.0,
          "all": 80.0
        },
        "2011": {
          "Buddhist": 170.0,
          "Christian": 62.0,
          "Hindu": 47.0,
          "Jewish": 73.0,
          "Muslim": 88.0,
          "Noreligion": 108.0,
          "Otherreligion": 149.0,
          "Religionnotstated": 97.0,
          "Sikh": 24.0,
          "all": 84.0
        },
        "change": {
          "Buddhist": 323.0,
          "Christian": 224.0,
          "Hindu": 106.0,
          "Jewish": 208.0,
          "Muslim": 7.0,
          "Noreligion": 197.0,
          "Otherreligion": 83.0,
          "Religionnotstated": 200.0,
          "Sikh": 16.0,
          "all": 256.0
        }
      }
    },
    "ethnicity": {
      "perc": {
        "2001": {
          "asian": 2.88,
          "black": 0.95,
          "mixed": 1.29,
          "other": 0.29,
          "white": 94.59
        },
        "2011": {
          "asian": 6.56,
          "black": 1.57,
          "mixed": 2.13,
          "other": 0.59,
          "white": 89.15
        },
        "change": {
          "asian": 3.68,
          "black": 0.62,
          "mixed": 0.84,
          "other": 0.3,
          "white": -5.44
        }
      },
      "perc_rank": {
        "2001": {
          "asian": 102.0,
          "black": 76.0,
          "mixed": 77.0,
          "other": 97.0,
          "white": 232.0
        },
        "2011": {
          "asian": 88.0,
          "black": 92.0,
          "mixed": 88.0,
          "other": 103.0,
          "white": 235.0
        },
        "change": {
          "asian": 60.0,
          "black": 103.0,
          "mixed": 102.0,
          "other": 96.0,
          "white": 247.0
        }
      },
      "value": {
        "2001": {
          "all": 199517.0,
          "asian": 5745.0,
          "black": 1895.0,
          "mixed": 2565.0,
          "other": 587.0,
          "white": 188725.0
        },
        "2011": {
          "all": 206674.0,
          "asian": 13561.0,
          "black": 3239.0,
          "mixed": 4404.0,
          "other": 1226.0,
          "white": 184244.0
        },
        "change": {
          "all": 3.59,
          "asian": 136.05,
          "black": 70.92,
          "mixed": 71.7,
          "other": 108.86,
          "white": -2.37
        }
      },
      "value_rank": {
        "2001": {
          "all": 80.0,
          "asian": 88.0,
          "black": 65.0,
          "mixed": 66.0,
          "other": 73.0,
          "white": 62.0
        },
        "2011": {
          "all": 84.0,
          "asian": 77.0,
          "black": 79.0,
          "mixed": 73.0,
          "other": 81.0,
          "white": 68.0
        },
        "change": {
          "all": 256.0,
          "asian": 85.0,
          "black": 229.0,
          "mixed": 264.0,
          "other": 133.0,
          "white": 272.0
        }
      }
    },
    "health": {
      "perc": {
        "2001": {
          "bad": 8.0,
          "fair": 21.1,
          "good": 70.89
        },
        "2011": {
          "bad": 5.2,
          "fair": 13.09,
          "good": 81.71
        },
        "change": {
          "bad": -2.8,
          "fair": -8.01,
          "good": 10.82
        }
      },
      "perc_rank": {
        "2001": {
          "bad": 204.0,
          "fair": 246.0,
          "good": 104.0
        },
        "2011": {
          "bad": 171.0,
          "fair": 185.0,
          "good": 158.0
        },
        "change": {
          "bad": 85.0,
          "fair": 42.0,
          "good": 325.0
        }
      },
      "value": {
        "2001": {
          "all": 199517.0,
          "bad": 15966.0,
          "fair": 42107.0,
          "good": 141444.0
        },
        "2011": {
          "all": 206674.0,
          "bad": 10738.0,
          "fair": 27056.0,
          "good": 168880.0
        },
        "change": {
          "all": 3.59,
          "bad": -32.74,
          "fair": -35.74,
          "good": 19.4
        }
      },
      "value_rank": {
        "2001": {
          "all": 80.0,
          "bad": 99.0,
          "fair": 86.0,
          "good": 75.0
        },
        "2011": {
          "all": 84.0,
          "bad": 99.0,
          "fair": 85.0,
          "good": 86.0
        },
        "change": {
          "all": 256.0,
          "bad": 93.0,
          "fair": 152.0,
          "good": 303.0
        }
      }
    },
    "economic": {
      "perc": {
        "2001": {
          "employee": 55.52,
          "inactive": 31.25,
          "self-employed": 7.96,
          "student": 2.31,
          "unemployed": 2.96
        },
        "2011": {
          "employee": 54.54,
          "inactive": 29.15,
          "self-employed": 9.22,
          "student": 2.84,
          "unemployed": 4.25
        },
        "change": {
          "employee": -0.98,
          "inactive": -2.1,
          "self-employed": 1.26,
          "student": 0.53,
          "unemployed": 1.29
        }
      },
      "perc_rank": {
        "2001": {
          "employee": 97.0,
          "inactive": 197.0,
          "self-employed": 208.0,
          "student": 146.0,
          "unemployed": 157.0
        },
        "2011": {
          "employee": 106.0,
          "inactive": 187.0,
          "self-employed": 208.0,
          "student": 137.0,
          "unemployed": 132.0
        },
        "change": {
          "employee": 222.0,
          "inactive": 105.0,
          "self-employed": 157.0,
          "student": 176.0,
          "unemployed": 89.0
        }
      },
      "value": {
        "2001": {
          "all": 142437.0,
          "employee": 79084.0,
          "inactive": 44507.0,
          "self-employed": 11337.0,
          "student": 3289.0,
          "unemployed": 4220.0
        },
        "2011": {
          "all": 148360.0,
          "employee": 80913.0,
          "inactive": 43252.0,
          "self-employed": 13673.0,
          "student": 4218.0,
          "unemployed": 6304.0
        },
        "change": {
          "all": 4.16,
          "employee": 2.31,
          "inactive": -2.82,
          "self-employed": 20.61,
          "student": 28.25,
          "unemployed": 49.38
        }
      },
      "value_rank": {
        "2001": {
          "all": 83.0,
          "employee": 72.0,
          "inactive": 89.0,
          "self-employed": 73.0,
          "student": 97.0,
          "unemployed": 97.0
        },
        "2011": {
          "all": 90.0,
          "employee": 85.0,
          "inactive": 95.0,
          "self-employed": 82.0,
          "student": 105.0,
          "unemployed": 99.0
        },
        "change": {
          "all": 277.0,
          "employee": 295.0,
          "inactive": 216.0,
          "self-employed": 216.0,
          "student": 233.0,
          "unemployed": 146.0
        }
      }
    },
    "children": {
      "perc": {
        "2001": {
          "Kids": 31.53,
          "NoKids": 57.4,
          "NonDepKids": 11.08
        },
        "2011": {
          "Kids": 30.17,
          "NoKids": 58.25,
          "NonDepKids": 11.59
        },
        "change": {
          "Kids": -1.36,
          "NoKids": 0.85,
          "NonDepKids": 0.51
        }
      },
      "perc_rank": {
        "2001": {
          "Kids": 74.0,
          "NoKids": 286.0,
          "NonDepKids": 35.0
        },
        "2011": {
          "Kids": 106.0,
          "NoKids": 265.0,
          "NonDepKids": 31.0
        },
        "change": {
          "Kids": 202.0,
          "NoKids": 157.0,
          "NonDepKids": 97.0
        }
      },
      "value": {
        "2001": {
          "Kids": 25517.0,
          "NoKids": 46450.0,
          "NonDepKids": 8963.0,
          "all": 80930.0
        },
        "2011": {
          "Kids": 25959.0,
          "NoKids": 50127.0,
          "NonDepKids": 9970.0,
          "all": 86056.0
        },
        "change": {
          "Kids": 1.73,
          "NoKids": 7.92,
          "NonDepKids": 11.24,
          "all": 6.33
        }
      },
      "value_rank": {
        "2001": {
          "Kids": 79.0,
          "NoKids": 96.0,
          "NonDepKids": 62.0,
          "all": 85.0
        },
        "2011": {
          "Kids": 86.0,
          "NoKids": 93.0,
          "NonDepKids": 61.0,
          "all": 88.0
        },
        "change": {
          "Kids": 230.0,
          "NoKids": 193.0,
          "NonDepKids": 143.0,
          "all": 216.0
        }
      }
    },
    "household": {
      "perc": {
        "2001": {
          "65andOver": 10.85,
          "Cohabiting": 6.8,
          "LoneParent": 9.32,
          "Married": 42.26,
          "OnePerson": 26.27,
          "Other": 4.5
        },
        "2011": {
          "65andOver": 10.23,
          "Cohabiting": 7.8,
          "LoneParent": 10.83,
          "Married": 36.78,
          "OnePerson": 29.17,
          "Other": 5.19
        },
        "change": {
          "65andOver": -0.62,
          "Cohabiting": 1.0,
          "LoneParent": 1.51,
          "Married": -5.48,
          "OnePerson": 2.9,
          "Other": 0.69
        }
      },
      "perc_rank": {
        "2001": {
          "65andOver": 79.0,
          "Cohabiting": 307.0,
          "LoneParent": 129.0,
          "Married": 77.0,
          "OnePerson": 268.0,
          "Other": 251.0
        },
        "2011": {
          "65andOver": 97.0,
          "Cohabiting": 320.0,
          "LoneParent": 118.0,
          "Married": 110.0,
          "OnePerson": 167.0,
          "Other": 240.0
        },
        "change": {
          "65andOver": 162.0,
          "Cohabiting": 270.0,
          "LoneParent": 76.0,
          "Married": 298.0,
          "OnePerson": 16.0,
          "Other": 185.0
        }
      },
      "value": {
        "2001": {
          "65andOver": 8782.0,
          "Cohabiting": 5503.0,
          "LoneParent": 7542.0,
          "Married": 34203.0,
          "OnePerson": 21261.0,
          "Other": 3639.0,
          "all": 80930.0
        },
        "2011": {
          "65andOver": 8801.0,
          "Cohabiting": 6714.0,
          "LoneParent": 9319.0,
          "Married": 31655.0,
          "OnePerson": 25102.0,
          "Other": 4465.0,
          "all": 86056.0
        },
        "change": {
          "65andOver": 0.22,
          "Cohabiting": 22.01,
          "LoneParent": 23.56,
          "Married": -7.45,
          "OnePerson": 18.07,
          "Other": 22.7,
          "all": 6.33
        }
      },
      "value_rank": {
        "2001": {
          "65andOver": 46.0,
          "Cohabiting": 113.0,
          "LoneParent": 90.0,
          "Married": 52.0,
          "OnePerson": 102.0,
          "Other": 117.0,
          "all": 85.0
        },
        "2011": {
          "65andOver": 43.0,
          "Cohabiting": 116.0,
          "LoneParent": 92.0,
          "Married": 59.0,
          "OnePerson": 93.0,
          "Other": 119.0,
          "all": 88.0
        },
        "change": {
          "65andOver": 166.0,
          "Cohabiting": 242.0,
          "LoneParent": 131.0,
          "Married": 281.0,
          "OnePerson": 38.0,
          "Other": 186.0,
          "all": 216.0
        }
      }
    },
    "marital": {
      "perc": {
        "2001": {
          "Married": 57.28,
          "Seperated": 9.09,
          "Single": 25.2,
          "Widowed": 8.43
        },
        "2011": {
          "Married": 51.7,
          "Seperated": 10.41,
          "Single": 30.08,
          "Widowed": 7.81
        },
        "change": {
          "Married": -5.58,
          "Seperated": 1.32,
          "Single": 4.88,
          "Widowed": -0.62
        }
      },
      "perc_rank": {
        "2001": {
          "Married": 70.0,
          "Seperated": 303.0,
          "Single": 223.0,
          "Widowed": 165.0
        },
        "2011": {
          "Married": 111.0,
          "Seperated": 289.0,
          "Single": 195.0,
          "Widowed": 110.0
        },
        "change": {
          "Married": 286.0,
          "Seperated": 172.0,
          "Single": 108.0,
          "Widowed": 41.0
        }
      },
      "value": {
        "2001": {
          "Married": 90328.0,
          "Seperated": 14332.0,
          "Single": 39750.0,
          "Widowed": 13298.0,
          "all": 157708.0
        },
        "2011": {
          "Married": 86602.0,
          "Seperated": 17434.0,
          "Single": 50382.0,
          "Widowed": 13075.0,
          "all": 167493.0
        },
        "change": {
          "Married": -4.12,
          "Seperated": 21.64,
          "Single": 26.75,
          "Widowed": -1.68,
          "all": 6.2
        }
      },
      "value_rank": {
        "2001": {
          "Married": 56.0,
          "Seperated": 108.0,
          "Single": 106.0,
          "Widowed": 75.0,
          "all": 80.0
        },
        "2011": {
          "Married": 64.0,
          "Seperated": 102.0,
          "Single": 105.0,
          "Widowed": 64.0,
          "all": 84.0
        },
        "change": {
          "Married": 273.0,
          "Seperated": 159.0,
          "Single": 130.0,
          "Widowed": 66.0,
          "all": 245.0
        }
      }
    },
    "travel": {
      "perc": {
        "2001": {
          "bicycle": 1.6,
          "bus": 9.5,
          "car_van": 71.11,
          "foot": 5.64,
          "home": 9.24,
          "moto": 0.84,
          "other": 0.19,
          "taxi": 0.37,
          "train_metro": 1.51
        },
        "2011": {
          "bicycle": 1.39,
          "bus": 8.12,
          "car_van": 72.18,
          "foot": 6.12,
          "home": 5.32,
          "moto": 0.51,
          "other": 0.45,
          "taxi": 0.35,
          "train_metro": 5.57
        },
        "change": {
          "bicycle": -0.21,
          "bus": -1.38,
          "car_van": 1.07,
          "foot": 0.48,
          "home": -3.92,
          "moto": -0.33,
          "other": 0.26,
          "taxi": -0.02,
          "train_metro": 4.06
        }
      },
      "perc_rank": {
        "2001": {
          "bicycle": 250.0,
          "bus": 59.0,
          "car_van": 51.0,
          "foot": 327.0,
          "home": 205.0,
          "moto": 249.0,
          "other": 326.0,
          "taxi": 199.0,
          "train_metro": 129.0
        },
        "2011": {
          "bicycle": 252.0,
          "bus": 73.0,
          "car_van": 117.0,
          "foot": 325.0,
          "home": 171.0,
          "moto": 295.0,
          "other": 309.0,
          "taxi": 188.0,
          "train_metro": 108.0
        },
        "change": {
          "bicycle": 148.0,
          "bus": 284.0,
          "car_van": 196.0,
          "foot": 124.0,
          "home": 107.0,
          "moto": 221.0,
          "other": 136.0,
          "taxi": 141.0,
          "train_metro": 94.0
        }
      },
      "value": {
        "2001": {
          "all": 92514.0,
          "bicycle": 1483.0,
          "bus": 8787.0,
          "car_van": 65783.0,
          "foot": 5219.0,
          "home": 8549.0,
          "moto": 779.0,
          "other": 179.0,
          "taxi": 340.0,
          "train_metro": 1395.0
        },
        "2011": {
          "all": 97941.0,
          "bicycle": 1361.0,
          "bus": 7954.0,
          "car_van": 70690.0,
          "foot": 5991.0,
          "home": 5208.0,
          "moto": 495.0,
          "other": 442.0,
          "taxi": 343.0,
          "train_metro": 5457.0
        },
        "change": {
          "all": 5.87,
          "bicycle": -8.23,
          "bus": -9.48,
          "car_van": 7.46,
          "foot": 14.79,
          "home": -39.08,
          "moto": -36.46,
          "other": 146.93,
          "taxi": 0.88,
          "train_metro": 291.18
        }
      },
      "value_rank": {
        "2001": {
          "all": 73.0,
          "bicycle": 160.0,
          "bus": 60.0,
          "car_van": 51.0,
          "foot": 189.0,
          "home": 62.0,
          "moto": 102.0,
          "other": 194.0,
          "taxi": 119.0,
          "train_metro": 102.0
        },
        "2011": {
          "all": 88.0,
          "bicycle": 180.0,
          "bus": 77.0,
          "car_van": 53.0,
          "foot": 194.0,
          "home": 79.0,
          "moto": 161.0,
          "other": 143.0,
          "taxi": 132.0,
          "train_metro": 91.0
        },
        "change": {
          "all": 256.0,
          "bicycle": 236.0,
          "bus": 247.0,
          "car_van": 234.0,
          "foot": 191.0,
          "home": 201.0,
          "moto": 289.0,
          "other": 77.0,
          "taxi": 214.0,
          "train_metro": 173.0
        }
      }
    },
    "hoursworked": {
      "perc": {
        "2001": {
          "Female1-15": 6.47,
          "Female16-30": 14.02,
          "Female31-48": 22.98,
          "Female49plus": 2.82,
          "Male1-15": 1.85,
          "Male16-30": 2.86,
          "Male31-48": 36.12,
          "Male49plus": 12.87
        },
        "2011": {
          "Female1-15": 6.71,
          "Female16-30": 15.16,
          "Female31-48": 23.39,
          "Female49plus": 2.87,
          "Male1-15": 2.83,
          "Male16-30": 4.35,
          "Male31-48": 34.48,
          "Male49plus": 10.22
        },
        "change": {
          "Female1-15": 0.24,
          "Female16-30": 1.14,
          "Female31-48": 0.41,
          "Female49plus": 0.05,
          "Male1-15": 0.98,
          "Male16-30": 1.49,
          "Male31-48": -1.64,
          "Male49plus": -2.65
        }
      },
      "perc_rank": {
        "2001": {
          "Female1-15": 201.0,
          "Female16-30": 118.0,
          "Female31-48": 138.0,
          "Female49plus": 205.0,
          "Male1-15": 169.0,
          "Male16-30": 241.0,
          "Male31-48": 143.0,
          "Male49plus": 192.0
        },
        "2011": {
          "Female1-15": 173.0,
          "Female16-30": 141.0,
          "Female31-48": 113.0,
          "Female49plus": 183.0,
          "Male1-15": 191.0,
          "Male16-30": 227.0,
          "Male31-48": 169.0,
          "Male49plus": 176.0
        },
        "change": {
          "Female1-15": 123.0,
          "Female16-30": 215.0,
          "Female31-48": 116.0,
          "Female49plus": 79.0,
          "Male1-15": 217.0,
          "Male16-30": 187.0,
          "Male31-48": 232.0,
          "Male49plus": 93.0
        }
      },
      "value": {
        "2001": {
          "Female1-15": 6044.0,
          "Female16-30": 13098.0,
          "Female31-48": 21465.0,
          "Female49plus": 2634.0,
          "Male1-15": 1731.0,
          "Male16-30": 2674.0,
          "Male31-48": 33733.0,
          "Male49plus": 12021.0,
          "all": 93400.0
        },
        "2011": {
          "Female1-15": 6570.0,
          "Female16-30": 14846.0,
          "Female31-48": 22908.0,
          "Female49plus": 2807.0,
          "Male1-15": 2768.0,
          "Male16-30": 4264.0,
          "Male31-48": 33769.0,
          "Male49plus": 10009.0,
          "all": 97941.0
        },
        "change": {
          "Female1-15": 8.7,
          "Female16-30": 13.35,
          "Female31-48": 6.72,
          "Female49plus": 6.57,
          "Male1-15": 59.91,
          "Male16-30": 59.46,
          "Male31-48": 0.11,
          "Male49plus": -16.74,
          "all": 4.86
        }
      },
      "value_rank": {
        "2001": {
          "Female1-15": 60.0,
          "Female16-30": 56.0,
          "Female31-48": 84.0,
          "Female49plus": 81.0,
          "Male1-15": 72.0,
          "Male16-30": 96.0,
          "Male31-48": 74.0,
          "Male49plus": 67.0,
          "all": 73.0
        },
        "2011": {
          "Female1-15": 73.0,
          "Female16-30": 73.0,
          "Female31-48": 91.0,
          "Female49plus": 82.0,
          "Male1-15": 93.0,
          "Male16-30": 102.0,
          "Male31-48": 88.0,
          "Male49plus": 76.0,
          "all": 88.0
        },
        "change": {
          "Female1-15": 207.0,
          "Female16-30": 309.0,
          "Female31-48": 257.0,
          "Female49plus": 180.0,
          "Male1-15": 265.0,
          "Male16-30": 209.0,
          "Male31-48": 303.0,
          "Male49plus": 206.0,
          "all": 290.0
        }
      }
    },
    "tenure": {
      "perc": {
        "2001": {
          "owned": 78.2,
          "rent_free": 1.05,
          "rented_private": 4.18,
          "rented_social": 16.1,
          "shared_ownership": 0.47
        },
        "2011": {
          "owned": 73.86,
          "rent_free": 0.74,
          "rented_private": 9.88,
          "rented_social": 14.91,
          "shared_ownership": 0.61
        },
        "change": {
          "owned": -4.34,
          "rent_free": -0.31,
          "rented_private": 5.7,
          "rented_social": -1.19,
          "shared_ownership": 0.14
        }
      },
      "perc_rank": {
        "2001": {
          "owned": 45.0,
          "rent_free": 315.0,
          "rented_private": 324.0,
          "rented_social": 141.0,
          "shared_ownership": 203.0
        },
        "2011": {
          "owned": 42.0,
          "rent_free": 328.0,
          "rented_private": 317.0,
          "rented_social": 146.0,
          "shared_ownership": 173.0
        },
        "change": {
          "owned": 170.0,
          "rent_free": 48.0,
          "rented_private": 179.0,
          "rented_social": 209.0,
          "shared_ownership": 139.0
        }
      },
      "value": {
        "2001": {
          "all": 81316.0,
          "owned": 63586.0,
          "rent_free": 850.0,
          "rented_private": 3400.0,
          "rented_social": 13094.0,
          "shared_ownership": 386.0
        },
        "2011": {
          "all": 86056.0,
          "owned": 63559.0,
          "rent_free": 634.0,
          "rented_private": 8502.0,
          "rented_social": 12834.0,
          "shared_ownership": 527.0
        },
        "change": {
          "all": 5.83,
          "owned": -0.04,
          "rent_free": -25.41,
          "rented_private": 150.06,
          "rented_social": -1.99,
          "shared_ownership": 36.53
        }
      },
      "value_rank": {
        "2001": {
          "all": 84.0,
          "owned": 57.0,
          "rent_free": 215.0,
          "rented_private": 222.0,
          "rented_social": 99.0,
          "shared_ownership": 125.0
        },
        "2011": {
          "all": 88.0,
          "owned": 54.0,
          "rent_free": 208.0,
          "rented_private": 157.0,
          "rented_social": 102.0,
          "shared_ownership": 108.0
        },
        "change": {
          "all": 210.0,
          "owned": 183.0,
          "rent_free": 133.0,
          "rented_private": 17.0,
          "rented_social": 226.0,
          "shared_ownership": 136.0
        }
      }
    },
    "density": {
      "value": {
        "2001": {
          "all": 11.19
        },
        "2011": {
          "all": 11.59
        },
        "change": {
          "all": 3.57
        }
      },
      "value_rank": {
        "2001": {
          "all": 123.0
        },
        "2011": {
          "all": 123.0
        },
        "change": {
          "all": 257.0
        }
      }
    },
    "age10yr": {
      "perc": {
        "2001": {
          "0-9": 12.36,
          "10-19": 13.38,
          "20-29": 9.54,
          "30-39": 14.6,
          "40-49": 13.77,
          "50-59": 14.37,
          "60-69": 9.84,
          "70-79": 4.48,
          "80plus": 7.65
        },
        "2011": {
          "0-9": 11.26,
          "10-19": 12.83,
          "20-29": 10.66,
          "30-39": 11.16,
          "40-49": 15.43,
          "50-59": 12.81,
          "60-69": 12.27,
          "70-79": 4.32,
          "80plus": 9.26
        },
        "change": {
          "0-9": -1.1,
          "10-19": -0.55,
          "20-29": 1.12,
          "30-39": -3.44,
          "40-49": 1.66,
          "50-59": -1.56,
          "60-69": 2.43,
          "70-79": -0.16,
          "80plus": 1.61
        }
      },
      "perc_rank": {
        "2001": {
          "0-9": 140.0,
          "10-19": 69.0,
          "20-29": 267.0,
          "30-39": 230.0,
          "40-49": 131.0,
          "50-59": 66.0,
          "60-69": 131.0,
          "70-79": 83.0,
          "80plus": 161.0
        },
        "2011": {
          "0-9": 178.0,
          "10-19": 55.0,
          "20-29": 222.0,
          "30-39": 248.0,
          "40-49": 103.0,
          "50-59": 158.0,
          "60-69": 117.0,
          "70-79": 129.0,
          "80plus": 89.0
        },
        "change": {
          "0-9": 247.0,
          "10-19": 150.0,
          "20-29": 96.0,
          "30-39": 248.0,
          "40-49": 86.0,
          "50-59": 305.0,
          "60-69": 132.0,
          "70-79": 212.0,
          "80plus": 20.0
        }
      },
      "value": {
        "2001": {
          "0-9": 24660.0,
          "10-19": 26693.0,
          "20-29": 19040.0,
          "30-39": 29129.0,
          "40-49": 27475.0,
          "50-59": 28673.0,
          "60-69": 19639.0,
          "70-79": 8937.0,
          "80plus": 15271.0,
          "all": 199517.0
        },
        "2011": {
          "0-9": 23266.0,
          "10-19": 26517.0,
          "20-29": 22029.0,
          "30-39": 23063.0,
          "40-49": 31889.0,
          "50-59": 26484.0,
          "60-69": 25360.0,
          "70-79": 8933.0,
          "80plus": 19133.0,
          "all": 206674.0
        },
        "change": {
          "0-9": -5.65,
          "10-19": -0.66,
          "20-29": 15.7,
          "30-39": -20.82,
          "40-49": 16.07,
          "50-59": -7.63,
          "60-69": 29.13,
          "70-79": -0.04,
          "80plus": 25.29,
          "all": 3.59
        }
      },
      "value_rank": {
        "2001": {
          "0-9": 84.0,
          "10-19": 79.0,
          "20-29": 121.0,
          "30-39": 95.0,
          "40-49": 76.0,
          "50-59": 50.0,
          "60-69": 65.0,
          "70-79": 56.0,
          "80plus": 72.0,
          "all": 80.0
        },
        "2011": {
          "0-9": 94.0,
          "10-19": 82.0,
          "20-29": 113.0,
          "30-39": 109.0,
          "40-49": 80.0,
          "50-59": 72.0,
          "60-69": 51.0,
          "70-79": 58.0,
          "80plus": 49.0,
          "all": 84.0
        },
        "change": {
          "0-9": 263.0,
          "10-19": 226.0,
          "20-29": 115.0,
          "30-39": 268.0,
          "40-49": 190.0,
          "50-59": 322.0,
          "60-69": 163.0,
          "70-79": 240.0,
          "80plus": 38.0,
          "all": 256.0
        }
      }
    },
    "agemed": {
      "value": {
        "2001": {
          "all": 40.0
        },
        "2011": {
          "all": 42.0
        },
        "change": {
          "all": 5.0
        }
      },
      "value_rank": {
        "2001": {
          "all": 84.0
        },
        "2011": {
          "all": 107.0
        },
        "change": {
          "all": 198.0
        }
      }
    }
  }
}